DFF.v
module DFF (D, S, R, clk, Q, Qb);
    input D, S, R, clk;
    wire w1, w2, w3, w4, w5, w6, w7, w8, w9, w10, w11, w12, Db, clkb;
    output Q, Qb;

    not(Db, D);
    not(clkb, clk);
    

    nand(w1, D, clk);
    nand(w2, clk, Db);
    nand(w3, w1, w4, S);
    nand(w4, w3, w2, R);
    nand(w5, w3, clkb);
    nand(w6, w4, clkb);
    nand(w7, w8, w5, S);
    nand(w8, w7, w6, R);

    assign Q = w7;
    assign Qb = w8;
    

endmodule

DFF_tb.v
`timescale 1ns/1ns
`include "DFF.v"

module DFF_tb;

reg D = 0, clk = 0, S = 1, R = 1;
wire Q, Qb;

DFF DFF0(D, S, R, clk, Q, Qb);

initial clk = 0;

always begin
    clk = ~clk;
    #10;
end

initial begin
    $monitor("At time %4t, clk = %d S = %d R = %d D = %d Q = %d Qb = %d", $time, clk, S, R, D, Q, Qb);
    $dumpfile("DFF.vcd");
    $dumpvars(0, DFF_tb);
    S=0; #4;
    S=1; #4;
    D=0; #45;
    D=1; #40;
    D=0; #40;
    $finish;
end

endmodule

DFF.vcd
$date
	Wed Sep 25 23:19:15 2024
$end
$version
	Icarus Verilog
$end
$timescale
	1ns
$end
$scope module DFF_tb $end
$var wire 1 ! Q $end
$var wire 1 " Qb $end
$var reg 1 # D $end
$var reg 1 $ R $end
$var reg 1 % S $end
$var reg 1 & clk $end
$scope module DFF0 $end
$var wire 1 ' D $end
$var wire 1 ( Db $end
$var wire 1 ! Q $end
$var wire 1 " Qb $end
$var wire 1 ) R $end
$var wire 1 * S $end
$var wire 1 + clk $end
$var wire 1 , clkb $end
$var wire 1 - w1 $end
$var wire 1 . w2 $end
$var wire 1 / w3 $end
$var wire 1 0 w4 $end
$var wire 1 1 w5 $end
$var wire 1 2 w6 $end
$var wire 1 3 w7 $end
$var wire 1 4 w8 $end
$upscope $end
$upscope $end
$enddefinitions $end
#0
$dumpvars
04
13
12
11
10
1/
0.
1-
0,
1+
0*
1)
1(
0'
1&
0%
1$
0#
0"
1!
$end
#4
0/
1%
1*
#10
0!
03
1"
14
02
1,
1.
0&
0+
#20
12
0,
0.
1&
1+
#30
02
1,
1.
0&
0+
#40
12
0,
0.
1&
1+
#50
02
1,
1.
0&
0+
#53
0(
1#
1'
#60
00
12
1/
0,
0-
1&
1+
#70
0"
04
1!
13
01
1,
1-
0&
0+
#80
11
0,
0-
1&
1+
#90
01
1,
1-
0&
0+
#93
1(
0#
0'
#100
0/
11
10
0,
0.
1&
1+
#110
0!
03
1"
14
02
1,
1.
0&
0+
#120
12
0,
0.
1&
1+
#130
02
1,
1.
0&
0+
